odoo9_addon_l10n_ch_pain_base-9.0.1.0.2-py2.7-nspkg.pth
odoo9_addon_l10n_ch_pain_base-9.0.1.0.2.dist-info/DESCRIPTION.rst
odoo9_addon_l10n_ch_pain_base-9.0.1.0.2.dist-info/METADATA
odoo9_addon_l10n_ch_pain_base-9.0.1.0.2.dist-info/RECORD
odoo9_addon_l10n_ch_pain_base-9.0.1.0.2.dist-info/WHEEL
odoo9_addon_l10n_ch_pain_base-9.0.1.0.2.dist-info/metadata.json
odoo9_addon_l10n_ch_pain_base-9.0.1.0.2.dist-info/namespace_packages.txt
odoo9_addon_l10n_ch_pain_base-9.0.1.0.2.dist-info/top_level.txt
odoo_addons/l10n_ch_pain_base/README.rst
odoo_addons/l10n_ch_pain_base/__init__.py
odoo_addons/l10n_ch_pain_base/__openerp__.py
odoo_addons/l10n_ch_pain_base/i18n/ca.po
odoo_addons/l10n_ch_pain_base/i18n/de.po
odoo_addons/l10n_ch_pain_base/i18n/es.po
odoo_addons/l10n_ch_pain_base/i18n/fi.po
odoo_addons/l10n_ch_pain_base/i18n/fr.po
odoo_addons/l10n_ch_pain_base/i18n/it.po
odoo_addons/l10n_ch_pain_base/i18n/l10n_ch_pain_base.pot
odoo_addons/l10n_ch_pain_base/i18n/nb_NO.po
odoo_addons/l10n_ch_pain_base/i18n/pt_BR.po
odoo_addons/l10n_ch_pain_base/models/__init__.py
odoo_addons/l10n_ch_pain_base/models/account_move_line.py
odoo_addons/l10n_ch_pain_base/models/account_payment_line.py
odoo_addons/l10n_ch_pain_base/models/account_payment_order.py
odoo_addons/l10n_ch_pain_base/views/account_payment_line.xml
odoo_addons/l10n_ch_pain_base/views/bank_payment_line.xml
